bitcoinpaygate-0.3.dist-info/RECORD
bitcoinpaygate-0.3.dist-info/top_level.txt
bitcoinpaygate-0.3.dist-info/metadata.json
bitcoinpaygate-0.3.dist-info/METADATA
bitcoinpaygate-0.3.dist-info/DESCRIPTION.rst
bitcoinpaygate-0.3.dist-info/WHEEL
bitcoinpaygate/__init__.py
bitcoinpaygate/utils.py
bitcoinpaygate/communication.py
bitcoinpaygate/client.py
