Metadata-Version: 2.0
Name: bitcoinpaygate
Version: 0.3
Summary: The python client for Bitcoinpaygate API
Home-page: https://github.com/bitcoinpaygate/python-api-client
Author: Bitcoinpaygate
Author-email: support@bitcoinpaygate.com
License: MIT
Platform: UNKNOWN
Requires-Dist: requests
